qb-sdk/__init__.py
qbsdk/__init__.py
qbsdk/api.py
qbsdk/error.py
qbsdk/loyalty_token.py
qbsdk/wallet.py
qb_sdk-0.0.3.dist-info/LICENSE
qb_sdk-0.0.3.dist-info/METADATA
qb_sdk-0.0.3.dist-info/WHEEL
qb_sdk-0.0.3.dist-info/top_level.txt
qb_sdk-0.0.3.dist-info/RECORD
