Metadata-Version: 2.1
Name: qb-sdk
Version: 0.0.3
Summary: qiibee loyalty blockchain brand SDK
Home-page: https://github.com/qiibee/qb-sdk-python
Author: qiibee
Author-email: tech@qiibee.com
License: UNKNOWN
Keywords: qiibee,api,sdk,blockchain,loyalty,QBX
Platform: UNKNOWN
Classifier: Programming Language :: Python :: 3
Classifier: Programming Language :: Python :: 3.6
Classifier: License :: OSI Approved :: MIT License
Classifier: Operating System :: OS Independent
Requires-Python: >=3.6
Requires-Dist: requests (>=1.0.0)
Requires-Dist: web3 (>=5.0.0)
Requires-Dist: eth-utils (<2.0.0,>=1.6.0)
Requires-Dist: eth-keys (<0.3.0,>=0.2.1)
Requires-Dist: backoff (<2.0.0,>=1.9.0)
